edutesting/__init__.py
edutesting/bparallel/README.rst
edutesting/bparallel/__init__.py
edutesting/bparallel/__main__.py
edutesting/bparallel/bparallel.py
edutesting/contingent/__init__.py
edutesting/contingent/helpers.py
edutesting/contingent/xml_objects.py
edutesting/contingent/steps/__init__.py
edutesting/contingent/steps/exchange_steps.py
edutesting/docs/Makefile
edutesting/docs/__init__.py
edutesting/docs/conf.py
edutesting/docs/generate_behave_steps_doc.sh
edutesting/docs/index.rst
edutesting/docs/split_behave_doc.py
edutesting/factories/__init__.py
edutesting/factories/helpers.py
edutesting/formatters/README.rst
edutesting/formatters/__init__.py
edutesting/formatters/allure_formatter.py
edutesting/formatters/helpers.py
edutesting/jira_helpers/__init__.py
edutesting/jira_helpers/jira_helpers.py
edutesting/mocks/__init__.py
edutesting/mocks/datatransfer_server.py
edutesting/mocks/settings.py
edutesting/objectpack_integration_tests/README.rst
edutesting/objectpack_integration_tests/__init__.py
edutesting/objectpack_integration_tests/base_test.py
edutesting/objectpack_integration_tests/helpers.py
edutesting/objectpack_integration_tests/integration_test.py
edutesting/objectpack_integration_tests/soappy_client_transport.py
edutesting/objectpack_integration_tests/unit_test.py
edutesting/testlink_helpers/__init__.py
edutesting/testlink_helpers/tsl.py
edutesting/ui_steps/__init__.py
edutesting/ui_steps/desktop_steps.py
edutesting/ui_steps/field_steps.py
edutesting/ui_steps/grid_steps.py
edutesting/ui_steps/helpers.py
edutesting/ui_steps/login.py
edutesting/ui_steps/ui.py
edutesting/ui_steps/winobject.py
edutesting/ui_steps/js_scripts/README.rst
edutesting/ui_steps/js_scripts/SJTXE.js
edutesting/ui_steps/js_scripts/esprima.js
edutesting/ui_steps/js_scripts/helpers.js
edutesting/ui_steps/js_scripts/journal.js
edutesting/ui_steps/js_scripts/ui.js
edutesting/ui_steps/js_scripts/winobject.js
edutesting/xvfb_helpers/__init__.py
edutesting/xvfb_helpers/decorator.py
edutesting-0.7.0.dist-info/METADATA
edutesting-0.7.0.dist-info/WHEEL
edutesting-0.7.0.dist-info/entry_points.txt
edutesting-0.7.0.dist-info/top_level.txt
edutesting-0.7.0.dist-info/RECORD
