Metadata-Version: 2.1
Name: edutesting
Version: 0.7.0
Summary: Общая кодовая база для автотестов
Home-page: https://stash.bars-open.ru/projects/EDUBASE/repos/edutesting
Author: BARS Group
Requires-Dist: behave <1.3,>=1.2.6
Requires-Dist: TestLink-API-Python-client <0.7,>=0.6.4
Requires-Dist: selenium ==2.52
Requires-Dist: sphinx <8,>=3.5.4
Requires-Dist: sphinx-rtd-theme <4,>=2.0.0
Requires-Dist: jira <2.1.0,>=2.0.0
Requires-Dist: pem ==16.1.0
Requires-Dist: waiting ==1.4.1
Requires-Dist: xvfbwrapper ==0.2.9
Requires-Dist: beautifulsoup4 <4.10,>=4.8.2
